flash1dkmeans/__init__.py
flash1dkmeans/config.py
flash1dkmeans/k_cluster.py
flash1dkmeans/main.py
flash1dkmeans/two_cluster.py
flash1dkmeans/utils.py
flash1dkmeans-0.2.3.dist-info/METADATA
flash1dkmeans-0.2.3.dist-info/WHEEL
flash1dkmeans-0.2.3.dist-info/licenses/LICENSE
flash1dkmeans-0.2.3.dist-info/RECORD
