Metadata-Version: 2.4
Name: flash1dkmeans
Version: 0.2.3
Summary: An optimized K-means implementation for the one-dimensional case.
Project-URL: Homepage, https://github.com/SyphonArch/flash1dkmeans
Project-URL: Issues, https://github.com/SyphonArch/flash1dkmeans/issues
Author-email: Jake Hyun <jake.hyun@hotmail.com>
License-File: LICENSE
Classifier: License :: OSI Approved :: MIT License
Classifier: Operating System :: OS Independent
Classifier: Programming Language :: Python :: 3
Requires-Python: >=3.8
Requires-Dist: numba>=0.60.0
Requires-Dist: numpy>=1.26
